TNSA/__init__.py
TNSA/ns.py
TNSA_NS-0.1.0.dist-info/METADATA
TNSA_NS-0.1.0.dist-info/WHEEL
TNSA_NS-0.1.0.dist-info/top_level.txt
TNSA_NS-0.1.0.dist-info/RECORD
