Metadata-Version: 2.1
Name: TNSA-NS
Version: 0.1.0
Summary: TNSA - NS IS A NEURAL NETWORK MODULE USED IN THE DEVELOPMENT OF NEURAL NETWORK PROCESSING
Home-page: UNKNOWN
Author: TNSA
Author-email: thishyakethabimalla@gmail.com
License: UNKNOWN
Platform: UNKNOWN
